{
    "$schema": "https://schema.management.azure.com/schemas/2019-04-01/deploymentParameters.json#",
    "contentVersion": "1.0.0.0",
    "parameters": {
        "storageaccountname": {
            "value": "azstgapril8143355661"
        },
        "virtualnetworkname": {
            "value": "matrix-eastus-dev-vnet"
        },
        "subnet-1": {
            "value": "matrix-eastus-dev-subnet-01"
        },
        "subnet-2": {
            "value": "matrix-eastus-dev-subnet-02"
    },
    "publicip": {
        "value": "matrix-eastus-dev-pubip-01"
    },
    "VM-1": {
        "value": "matrix-eastus-dev-vm-01"
    },
    "adminuser": {
        "value": "matrix"
    },
    "adminpassword": {
        "value": "Password@123"
    },
    "Publicip-02": {
        "value": "matrix-eastus-dev-pubip-02"
    }
   
   
    }
}